Workbook

Sheet Practice Status
A1: SIMULATED SCENARIO — FICTIONAL ONLY — NOT CUSTOMER EVIDENCE
A2: Imported as a separate practice aid from the user-provided workbook; source sheet: Research Status. Do not use these scenarios as real interviews or customer findings.
A5: Research status and use
A6: Source: user-provided P1-S03 / P1-S04 interview guide. Scenarios authored for this workbook.
A8: Item | B8: Status / guidance
A9: Company | B9: CAB Synergy
A10: Workbook purpose | B10: Prepare for five customer interviews using varied fictional answers to every script question.
A11: Real interviews conducted | B11: 0
A12: Simulated profiles | B12: 5
A13: P1-S03 status | B13: Interview preparation only. Recruitment and live interviews remain to be done.
A14: P1-S04 status | B14: The written examples place current behavior before the optional concept probe. No live interview adherence has been verified.
A15: P1-S05 status | B15: Incomplete. The synthesis is a worked example using fictional scenario counts, not actual participant evidence.
A16: Consent and privacy | B16: Opening responses describe scenario assumptions only. Obtain real note-taking permission and separate recording permission before each interview.
A17: Evidence handling | B17: Responses and scenario wording are fictional. Synthesis interpretations are separate. No names, employer names, contacts, source code, credentials, or confidential details are included.
A18: Recruitment | B18: Recruit five people who personally did a recent review. Continue toward eight if important perspectives are missing or responses conflict.
A19: Live interview sequence | B19: Opening and eligibility, recent review, effort and friction, alternatives and frequency, optional concept probe, close. Schedule 25–30 minutes.
A20: After each live interview | B20: Use a real participant ID, record actual workflow and wording, note counterevidence and deviations, and obtain permission for any follow-up. Keep contacts separately.
A21: Decision rule from the guide | B21: Continue discovery or revise the segment if fewer than three real independent participants describe the same meaningful problem, or existing alternatives solve it adequately. Positive concept reactions do not establish demand.
A22: Companion framework | B22: P1-S05-Interview-Synthesis-Framework.md was referenced in the guide but not supplied. This example follows only the synthesis instructions included in the pasted guide.

Sheet Practice Roster
A1: SIMULATED SCENARIO — FICTIONAL ONLY — NOT CUSTOMER EVIDENCE
A2: Imported as a separate practice aid from the user-provided workbook; source sheet: Interview Log. Do not use these scenarios as real interviews or customer findings.
A5: Interview log — examples and unused slots
A6: SIM-P1–SIM-P5 are fictional. P6–P8 are blank future slots. Do not count any row as completed research.
A8: Participant ID | B8: Research status | C8: Role | D8: Team-size band | E8: Trigger | F8: Sequence and handoffs | G8: Tools used | H8: Main friction: fictional wording | I8: Stall / rework | J8: Tracking and ownership | K8: Frequency | L8: What works well | M8: Counterevidence / objection | N8: Current-process-first sequence | O8: Follow-up permission
A9: SIM-P1 | B9: Simulated — not conducted | C9: AppSec engineer | D9: 11–25 software staff | E9: A new customer-facing API was approaching release. It added a new permission boundary, so the engineering lead requested a review. | F9: The lead opened a Jira request. I asked for the data flow and roles, met with the developer, agreed on scope, reviewed the design and code, tested in staging, and discussed findings. Developers fixed the release blockers. I retested those fixes and left lower-priority items in the backlog. | G9: Jira, Confluence, GitHub, an internal checklist, Burp Suite, and SAST and dependency-scan results. I used the scanner results as inputs, not as the entire review. | H9: Getting a complete picture before testing took the most coordination. I spent roughly three hours on questions and meetings across four days, compared with about six hours of review work. | I9: The diagram described the old flow. After a developer clarified the new boundary, I had to revise the scope and repeat part of the authorization testing. | J9: Restricted Jira issues held sanitized evidence, severity rationale, owners, and due dates. Confluence held the scope and decision summary. I linked the two rather than copying all findings into a separate report. | K9: Our internal checklist and Jira issue template help. They do not consistently tell the requester which artifacts must be ready before I start. | L9: The short kickoff with the developer helps. Keeping findings in the developers’ existing backlog also works, and I would preserve that. | M9: A second findings database would be a poor fit. Generic authentication checks without context would also add little to our existing checklist. | N9: Illustrated only; concept placed after questions 1–15. No real sequence was observed. | O9: No actual permission. No contact data recorded.
A10: SIM-P2 | B10: Simulated — not conducted | C10: Senior full-stack developer | D10: 6–10 software staff | E10: We added an administrator feature that changed which users could view account information. The technical lead asked us to review the permissions before release. | F10: We discussed the feature during planning, wrote the expected roles in a GitHub issue, ran automated checks, and reviewed the pull request. I tested each role in staging, opened issues for concerns, and retested the fixes. We released after the lead approved the remaining items. | G10: GitHub issues and pull requests, CI checks, dependency alerts, browser developer tools, and a small Markdown security checklist copied from a previous feature. | H10: Deciding which checks applied took the longest. I spent about four hours reviewing and another two hours discussing expected behavior. We do not have someone who does this full time. | I10: The intended administrator permissions were unclear. We tested one interpretation, then changed the requirements and repeated those cases. | J10: GitHub issues stored the evidence and assignee. Priority labels represented urgency, but we did not consistently document a separate security severity or rationale. | K10: We reuse a short Markdown checklist and older issues. An external consultant helped on a previous larger release, but we do not engage one for every feature. | L10: Pull request review and CI fit our normal work. The other developer catches mistakes early, and I would keep that lightweight approach. | M10: An enterprise-length workbook or a list of checks without explanations would be hard to use. It would not replace a specialist for a complex design. | N10: Illustrated only; concept placed after questions 1–15. No real sequence was observed. | O10: No actual permission. No contact data recorded.
A11: SIM-P3 | B11: Simulated — not conducted | C11: Platform engineer and security champion | D11: 11–25 software staff | E11: We introduced an integration that sent application data to a third-party service. The engineering lead asked for a review before enabling it for customers. | F11: We opened a Linear project, mapped the data flow, agreed on scope, and reviewed the integration and configuration. I tested access and failure behavior in staging. We created remediation issues, reviewed deployment changes, retested, and ran a follow-up check after rollout. | G11: Linear, GitHub, a diagram in our documentation, CI scanners, cloud configuration views, and a spreadsheet for the initial review checklist. | H11: Waiting for the right staging setup took the most time. The technical checks took around five hours, but the review stretched over nine business days because configuration and test access arrived in pieces. | I11: Staging initially used a different service identity and settings from the planned production setup. We corrected that and reran the affected tests. | J11: Linear held owners, priority, deadlines, and links to evidence. Severity decisions were in issue comments. The spreadsheet was a temporary checklist, not our remediation system. | K11: Our deployment checklist and Linear workflow help. The gap is getting a representative environment and knowing which team must supply each prerequisite. | L11: Having one application owner and one operations owner works. Reviewing configuration changes in pull requests also gives us a useful history. | M11: It would be a poor fit if it focused only on application code or required manually copying Linear issues into another tracker. | N11: Illustrated only; concept placed after questions 1–15. No real sequence was observed. | O11: No actual permission. No contact data recorded.
A12: SIM-P4 | B12: Simulated — not conducted | C12: Independent application-security consultant | D12: Client team: 6–10 software staff | E12: The client was preparing a major release and wanted an external assessment after changing its sign-in and account-management flows. | F12: We agreed on objectives and boundaries, collected prerequisite information, and checked access. I held a kickoff, reviewed design and implementation, tested staging, validated findings, and debriefed the lead. The client remediated findings, and I performed the agreed retest. | G12: My own intake and report templates, a scoped testing checklist, Burp Suite, code-review tools, and the client’s GitHub issues for remediation. | H12: Collecting usable prerequisites and arranging retests took the most coordination. The assessment used about 16 hours, with around three additional hours of coordination over two weeks. | I12: One required role account was missing at kickoff. I completed other areas first, then returned to the blocked tests after access arrived. | J12: The report held evidence and severity rationale. The client tracked owners and fixes in GitHub. I used an agreed retest list to map client tickets back to report findings. | K12: My own templates and checklist solve most of the documentation problem. The client’s issue tracker handles remediation ownership. | L12: Written scope, a prerequisite checklist, and a findings debrief work well. I already have reusable templates and do not want to replace them casually. | M12: I already have these templates. A generic kit would duplicate my work, and its value would depend on maintenance, adaptability, and substantive examples. | N12: Illustrated only; concept placed after questions 1–15. No real sequence was observed. | O12: No actual permission. No contact data recorded.
A13: SIM-P5 | B13: Simulated — not conducted | C13: Backend developer and security champion | D13: 11–25 software staff | E13: We changed an existing API’s authorization behavior. Our pull request template flags permission changes for a focused security review. | F13: The pull request linked the design note and updated role matrix. We selected applicable checks, ran CI, manually tested the changed paths, and wrote issues for concerns. Developers fixed them, tests were added, and we verified the release in staging before closure. | G13: GitHub pull requests and issue forms, a repository checklist, automated authorization tests, dependency scanning, and staging logs with sensitive details excluded. | H13: The manual authorization checks took the most time, about two hours. Coordination was less than an hour because the inputs and owners were already clear. | I13: There was no meaningful stall in this review. A small requirement question was answered in the pull request without repeating the review. | J13: GitHub issue forms require evidence, severity rationale, owner, and target release. The pull request links the issue, tests, and deployment record. | K13: Our repository checklist and GitHub forms already cover intake, findings, and remediation. We periodically compare the checklist with our own architecture and recent changes. | L13: Our required intake fields, stable test roles, regression tests, and linked deployment record work well. I would keep all of those. | M13: We already have the proposed workflow. A separate kit could create duplicate documentation, and templates cannot replace application-specific tests. | N13: Illustrated only; concept placed after questions 1–15. No real sequence was observed. | O13: No actual permission. No contact data recorded.
A14: P6 | B14: Not recruited
A15: P7 | B15: Not recruited
A16: P8 | B16: Not recruited

Sheet Practice Synthesis
A1: SIMULATED SCENARIO — FICTIONAL ONLY — NOT CUSTOMER EVIDENCE
A2: Imported as a separate practice aid from the user-provided workbook; source sheet: Interview Synthesis. Do not use these scenarios as real interviews or customer findings.
A5: CAB Synergy — simulated interview synthesis
A6: Fictional examples only. Actual interviews completed: 0. P1-S05 remains incomplete.
A8: Candidate theme | B8: Simulated IDs | C8: Scenario count | D8: Fictional examples and wording | E8: Counterevidence / existing alternatives | F8: Interpretation to test in real interviews
A9: Incomplete prerequisites delay reviews | B9: SIM-P1, SIM-P3, SIM-P4 | C9: 3 | D9: P1: current diagram arrived late. P3: staging differed from the intended deployment. P4: a role account was missing. | E9: P5 already has complete intake and maintained role accounts. P4 already owns a prerequisite checklist. | F9: Ask whether delays come from missing fields, access provisioning, or competing priorities. A template may address only the first.
A10: Unclear intended permissions cause rework | B10: SIM-P1, SIM-P2 | C10: 2 | D10: P1 revised scope after clarifying the new boundary. P2 repeated tests after intended administrator behavior changed. | E10: P5 supplies an updated role matrix in the pull request. | F10: Test whether an earlier role/behavior agreement reduces rework. Two fictional scenarios do not establish a real theme.
A11: Deployment verification is difficult | B11: SIM-P1, SIM-P3, SIM-P4 | C11: 3 | D11: P1: a merged fix did not identify the deployed version. P3 needed configuration and deployment linkage. P4 relied on client release evidence. | E11: P5 links deployment evidence. Jira, Linear, and GitHub can already store those links. | F11: A closure checklist may help if the missing step is documentation. Verify operational ownership before proposing a product.
A12: Developers need help selecting relevant checks | B12: SIM-P2 | C12: 1 | D12: P2: “I would like a clearer way to decide what to test for a particular change.” | E12: P1 has AppSec expertise. P4 has consultant templates. P5 has an established checklist. | F12: Explore developers acting as reviewers as a separate segment. Do not assume all small teams need the same depth.
A13: Avoid duplicating the existing issue tracker | B13: SIM-P1, SIM-P3, SIM-P4, SIM-P5 | C13: 4 | D13: These concept-probe responses favor reuse of Jira, Linear, GitHub, or established reports. | E13: This topic arose after the concept was introduced. It is prompted feedback, not unprompted demand evidence. | F13: If the concept is tested, examine copyable fields and integration with existing tools. Do not infer willingness to pay.
A14: Existing processes can be adequate | B14: SIM-P4, SIM-P5 | C14: 2 | D14: P4 already has reusable templates. P5 reports no meaningful stall and little need for process change. | E14: P2 lacks a specialist. P1 and P3 report coordination gaps despite existing tools. | F14: Keep these objections visible. Validate the target audience and whether existing alternatives solve the problem adequately.

Sheet Practice Responses
A1: SIMULATED SCENARIO — FICTIONAL ONLY — NOT CUSTOMER EVIDENCE
A2: Imported as a separate practice aid from the user-provided workbook; source sheet: Interview Responses. Do not use these scenarios as real interviews or customer findings.
A5: Five simulated customer interviews
A6: All first-person responses are invented for preparation. Questions follow current-process-first order.
A8: Participant ID | B8: Role | C8: Team-size band | D8: Section | E8: Question | F8: Simulated response
A9: SIM-P1 | B9: AppSec engineer | C9: 11–25 software staff | D9: Opening | E9: Role and personal participation | F9: I am the only AppSec engineer supporting about 18 engineers. In this scenario, I personally led the review.
A10: SIM-P1 | B10: AppSec engineer | C10: 11–25 software staff | D10: Opening | E10: Note-taking and recording permission | F10: Scenario assumes anonymized notes are allowed and recording is declined. No real permission was obtained.
A11: SIM-P1 | B11: AppSec engineer | C11: 11–25 software staff | D11: Recent review | E11: 1. What triggered the most recent review? | F11: A new customer-facing API was approaching release. It added a new permission boundary, so the engineering lead requested a review.
A12: SIM-P1 | B12: AppSec engineer | C12: 11–25 software staff | D12: Recent review | E12: 2. What was your role, and who else was involved? | F12: I scoped and performed the review. A backend lead explained the design, a developer supplied test access, and the engineering manager handled release decisions.
A13: SIM-P1 | B13: AppSec engineer | C13: 11–25 software staff | D13: Recent review | E13: 3. What happened first, next, and through follow-up? | F13: The lead opened a Jira request. I asked for the data flow and roles, met with the developer, agreed on scope, reviewed the design and code, tested in staging, and discussed findings. Developers fixed the release blockers. I retested those fixes and left lower-priority items in the backlog.
A14: SIM-P1 | B14: AppSec engineer | C14: 11–25 software staff | D14: Recent review | E14: 4. What information did you need, and where did you get it? | F14: I needed the API inventory, role matrix, data classification, authentication flow, and staging accounts. The API definition was in the repo, but the role matrix and current flow came from conversations and an updated diagram.
A15: SIM-P1 | B15: AppSec engineer | C15: 11–25 software staff | D15: Recent review | E15: 5. Which tools, documents, or checklists did you use? | F15: Jira, Confluence, GitHub, an internal checklist, Burp Suite, and SAST and dependency-scan results. I used the scanner results as inputs, not as the entire review.
A16: SIM-P1 | B16: AppSec engineer | C16: 11–25 software staff | D16: Recent review | E16: 6. What happened after a finding was identified? | F16: I validated the concern, wrote the affected behavior and impact in a Jira issue, discussed severity with the lead, and assigned an owner. The manager approved any deferred item with a due date. I retested before closing.
A17: SIM-P1 | B17: AppSec engineer | C17: 11–25 software staff | D17: Effort and friction | E17: 7. What took the most time or coordination? | F17: Getting a complete picture before testing took the most coordination. I spent roughly three hours on questions and meetings across four days, compared with about six hours of review work.
A18: SIM-P1 | B18: AppSec engineer | C18: 11–25 software staff | D18: Effort and friction | E18: 8. Where did progress stall or work need to be redone? | F18: The diagram described the old flow. After a developer clarified the new boundary, I had to revise the scope and repeat part of the authorization testing.
A19: SIM-P1 | B19: AppSec engineer | C19: 11–25 software staff | D19: Effort and friction | E19: 9. How were evidence, severity, owners, and remediation tracked? | F19: Restricted Jira issues held sanitized evidence, severity rationale, owners, and due dates. Confluence held the scope and decision summary. I linked the two rather than copying all findings into a separate report.
... A113: SIM-P5 | B113: Backend developer and security champion | C113: 11–25 software staff | D113: Close | E113: Referral and follow-up permission | F113: No actual referral or permission. I would ask the other reviewer before arranging any follow-up.

Sheet Practice Guide
A1: SIMULATED INTERVIEWS | PRACTICE ONLY
A3: The following imported sheets contain fictional scenarios supplied for rehearsal. They are not real customer interviews, must not be counted as participants or findings, and do not change interview progress.
A5: Purpose | B5: Practice the neutral interview sequence, answer coding, and counterevidence review.
A6: Source | B6: Application_Review_Kit_Simulated_Interviews Guide (2).xlsx (user-supplied).
A7: Real interviews in these practice scenarios | B7: 0
A8: Real interview log | B8: Use the separate Interview Log tab only for actual conversations.
A9: Real synthesis | B9: Use Interview Synthesis only after entering actual interviews and evidence.
A10: Identifier rule | B10: SIM-P1 through SIM-P5 are fictional scenario IDs. Never copy them into the live Interview Log as completed interviews.

Sheet Interview Synthesis
A1: P1-S05 | Interview Synthesis
A2: Candidate themes are prompts from the unvalidated hypothesis only - not findings. Enter evidence only after real interviews; use anonymous participant IDs and distinct counts.
A3: Completed interviews | B3: ='Interview Log'!B3 -> 0 | C3: Minimum target | D3: ='Interview Log'!D3 -> 5 | E3: Minimum target progress | F3: =IFERROR(MIN(B3/D3,1),0) -> 0 | G3: Themes mentioned unprompted by 3+ people | H3: =COUNTIF(F7:F14,">=3") -> 0 | I3: No interview evidence recorded yet.
A5: Coding rules: list each participant ID once per theme, separated by commas. Enter only IDs supported by interview notes. Keep evidence, anonymized wording, counterevidence, and interpretation separate. Interview counts are discovery input, not statistical proof.
A6: Candidate theme (prompt only) | B6: Evidence status | C6: Participant IDs (distinct) | D6: Distinct people | E6: Unprompted IDs | F6: Unprompted people | G6: Evidence / recent examples | H6: Participant wording (anonymized) | I6: Frequency / impact | J6: Current alternatives / workaround | K6: Counterevidence / objections | L6: Interpretation / next question
A7: Review preparation and context | B7: =IF(D7=0,"Unvalidated",IF(D7<3,"Emerging - needs more evidence","Review pattern; not proof")) -> Unvalidated | D7: =IF(C7="",0,LEN(C7)-LEN(SUBSTITUTE(C7,",",""))+1) -> 0 | F7: =IF(E7="",0,LEN(E7)-LEN(SUBSTITUTE(E7,",",""))+1) -> 0
A8: Review consistency and coverage | B8: =IF(D8=0,"Unvalidated",IF(D8<3,"Emerging - needs more evidence","Review pattern; not proof")) -> Unvalidated | D8: =IF(C8="",0,LEN(C8)-LEN(SUBSTITUTE(C8,",",""))+1) -> 0 | F8: =IF(E8="",0,LEN(E8)-LEN(SUBSTITUTE(E8,",",""))+1) -> 0
A9: Evidence and decision traceability | B9: =IF(D9=0,"Unvalidated",IF(D9<3,"Emerging - needs more evidence","Review pattern; not proof")) -> Unvalidated | D9: =IF(C9="",0,LEN(C9)-LEN(SUBSTITUTE(C9,",",""))+1) -> 0 | F9: =IF(E9="",0,LEN(E9)-LEN(SUBSTITUTE(E9,",",""))+1) -> 0
A10: Severity and recommendations | B10: =IF(D10=0,"Unvalidated",IF(D10<3,"Emerging - needs more evidence","Review pattern; not proof")) -> Unvalidated | D10: =IF(C10="",0,LEN(C10)-LEN(SUBSTITUTE(C10,",",""))+1) -> 0 | F10: =IF(E10="",0,LEN(E10)-LEN(SUBSTITUTE(E10,",",""))+1) -> 0
A11: Remediation ownership and follow-up | B11: =IF(D11=0,"Unvalidated",IF(D11<3,"Emerging - needs more evidence","Review pattern; not proof")) -> Unvalidated | D11: =IF(C11="",0,LEN(C11)-LEN(SUBSTITUTE(C11,",",""))+1) -> 0 | F11: =IF(E11="",0,LEN(E11)-LEN(SUBSTITUTE(E11,",",""))+1) -> 0
A12: Existing process sufficiency | B12: =IF(D12=0,"Unvalidated",IF(D12<3,"Emerging - needs more evidence","Review pattern; not proof")) -> Unvalidated | D12: =IF(C12="",0,LEN(C12)-LEN(SUBSTITUTE(C12,",",""))+1) -> 0 | F12: =IF(E12="",0,LEN(E12)-LEN(SUBSTITUTE(E12,",",""))+1) -> 0
A13: Audience fit and review cadence | B13: =IF(D13=0,"Unvalidated",IF(D13<3,"Emerging - needs more evidence","Review pattern; not proof")) -> Unvalidated | D13: =IF(C13="",0,LEN(C13)-LEN(SUBSTITUTE(C13,",",""))+1) -> 0 | F13: =IF(E13="",0,LEN(E13)-LEN(SUBSTITUTE(E13,",",""))+1) -> 0
A14: Unexpected themes (add only if heard) | B14: =IF(D14=0,"Unvalidated",IF(D14<3,"Emerging - needs more evidence","Review pattern; not proof")) -> Unvalidated | D14: =IF(C14="",0,LEN(C14)-LEN(SUBSTITUTE(C14,",",""))+1) -> 0 | F14: =IF(E14="",0,LEN(E14)-LEN(SUBSTITUTE(E14,",",""))+1) -> 0

Sheet Interview Log
A1: P1-S03 | Customer Interview Log
A2: Interview guide: | B2: P1-S03-Customer-Interview-Guide.md (saved in the project folder)
A3: Completed interviews | B3: =COUNTIF(D7:D14,"Completed") -> 0 | C3: Minimum target | D3: 5 | E3: Minimum target progress | F3: =MIN(B3/D3,1) -> 0 | G3: Participant slots | H3: =COUNTA(A7:A14) -> 8
A4: Real interviews only. Fictional SIM-P1–SIM-P5 examples are kept on Practice tabs and must not be entered or counted here.
A6: Participant ID | B6: Role / review experience | C6: Team-size band | D6: Contact status | E6: Interview date | F6: Review trigger | G6: Process / handoffs | H6: Tools used | I6: Friction (anonymized quote) | J6: Frequency / impact | K6: Workaround / alternatives | L6: What works well | M6: Evidence / interpretation | N6: Follow-up / permission | O6: Current-process-first followed?
A7: P1 | D7: Not contacted
A8: P2 | D8: Not contacted
A9: P3 | D9: Not contacted
A10: P4 | D10: Not contacted
A11: P5 | D11: Not contacted
A12: P6 | D12: Not contacted
A13: P7 | D13: Not contacted
A14: P8 | D14: Not contacted

Sheet Ongoing
A1: Ongoing Tasks
A2: Live view from Task Register; changes recalculate automatically.
A3: Task count | B3: =IFERROR(ROWS(_xlfn.ANCHORARRAY(A5)),0) -> 14 | D3: Average remaining | E3: =IFERROR(AVERAGE(_xlfn.ANCHORARRAY(H5)),0) -> 0.725
A4: Task ID | B4: Phase | C4: Plan Step | D4: Task | E4: Status | F4: Progress | G4: Notes | H4: Remaining
A5: {=_xlfn._xlws.FILTER('Task Register'!A2:G1001,'Task Register'!E2:E1001="Ongoing","")} -> P1-S02 | B5: Phase 1: Choose and validate the customer problem | C5: Step 2 | D5: Choose one primary audience and describe its review workflow, current tools, and pain points. | E5: Ongoing | F5: 0.5 | G5: Drafted P1-S02-Audience-Workflow-Hypothesis.md: selected AppSec reviewer at a small software team; documented a likely review workflow, tool categories, and pain-point hypotheses. These are not verified customer facts. Update after interviews with 5-8 target users. | H5: {=_xlfn._xlws.FILTER('Task Register'!H2:H1001,'Task Register'!E2:E1001="Ongoing","")} -> 0.5
A6: P1-S03 | B6: Phase 1: Choose and validate the customer problem | C6: Step 3 | D6: Speak with 5â€“8 people who match that audience. Ask about their current process, where work slows down, what they already use, and what would make a toolkit useful. | E6: Ongoing | F6: 0.1 | G6: Prepared P1-S03-Customer-Interview-Guide.md, neutral 25-30 minute interview script, invitation template, privacy guidance, synthesis criteria, and an eight-person Interview Log tab. No interviews have been conducted yet; this is preparation only. | H6: 0.9
A7: P1-S04 | B7: Phase 1: Choose and validate the customer problem | C7: Step 4 | D7: Avoid pitching the proposed product during the first part of each conversation; learn how customers work today. | E7: Ongoing | F7: 0.1 | G7: Added a P1-S04 current-process-first protocol to the interview guide: keep the product out of the opening/workflow questions, defer the optional concept probe until the last 2-3 minutes, and log deviations. No interviews have been conducted; preparation only. | H7: 0.9
A8: P1-S05 | B8: Phase 1: Choose and validate the customer problem | C8: Step 5 | D8: Summarize repeated needs, objections, existing alternatives, and language customers use. | E8: Ongoing | F8: 0.1 | G8: User-supplied fictional interview scenarios are in separate Practice tabs for rehearsal. They are not actual interviews or evidence; Interview Log remains at zero. P1-S05 remains ongoing pending real interview findings. | H8: 0.9
A9: P1-S06 | B9: Phase 1: Choose and validate the customer problem | C9: Step 6 | D9: Decide whether to proceed, revise the audience/problem, or test another toolkit idea. | E9: Ongoing | F9: 0.1 | G9: Prepared P1-S06-Customer-Problem-Decision-Framework.md with proceed, revise, retarget, and pause criteria. The actual decision remains blocked until at least five qualified customer interviews and synthesis are complete. | H9: 0.9
A10: P2-S01 | B10: Phase 2: Define the minimum useful toolkit | C10: Step 1 | D10: Write a one-sentence product promise focused on a practical task, not a guaranteed security outcome. | E10: Ongoing | F10: 0.25 | G10: Drafted a one-sentence workflow-support promise in P2-Application-Review-Kit-Product-Brief.md. Validate wording and problem importance with target users before finalizing. | H10: 0.75
A11: P2-S02 | B11: Phase 2: Define the minimum useful toolkit | C11: Step 2 | D11: Define the intended user, prerequisites, and situations where the toolkit is not suitable. | E11: Ongoing | F11: 0.25 | G11: Provisional intended user, prerequisites, and exclusions drafted in P2-Application-Review-Kit-Product-Brief.md. Audience and workflow remain unvalidated hypotheses. | H11: 0.75
A12: P2-S03 | B12: Phase 2: Define the minimum useful toolkit | C12: Step 3 | D12: Select only the worksheets, checklists, and templates necessary to complete the task. | E12: Ongoing | F12: 0.25 | G12: Six candidate resources in the existing catalog were organized as a provisional minimum set in P2-Application-Review-Kit-Product-Brief.md. Include/remove decisions await interviews and prototype feedback. | H12: 0.75
A13: P2-S04 | B13: Phase 2: Define the minimum useful toolkit | C13: Step 4 | D13: Describe the expected workflow: what the user provides, what they do with each resource, and what they finish with. | E13: Ongoing | F13: 0.3 | G13: Drafted a five-step intake-to-remediation workflow and expected outputs in P2-Application-Review-Kit-Product-Brief.md. Confirm with real users before treating as final. | H13: 0.7
A14: P2-S06 | B14: Phase 2: Define the minimum useful toolkit | C14: Step 6 | D14: Identify any security, privacy, licensing, accessibility, or compatibility considerations. | E14: Ongoing | F14: 0.2 | G14: Draft safeguards cover confidential data, authorization, licensing, accessibility, compatibility, and limitations in P2-Application-Review-Kit-Product-Brief.md. Review and validate before prototype or release. | H14: 0.8
A15: P6-S02 | B15: Phase 6: Update and test the website | C15: Step 2 | D15: Keep proposed information visibly labeled until it is confirmed; remove placeholder prices when they are no longer appropriate. | E15: Ongoing | F15: 0.5 | G15: Concept availability and proposed-pricing labels are in place; update/remove placeholders once the offer and price are validated. | H15: 0.5
A16: P6-S04 | B16: Phase 6: Update and test the website | C16: Step 4 | D16: Keep toolkit search, category filters, and comparison instructions understandable and test them with users. | E16: Ongoing | F16: 0.5 | G16: Comparison instructions and the page jump link were clarified; target-user testing of search, filters, and comparison remains. | H16: 0.5
A17: P6-S07 | B17: Phase 6: Update and test the website | C17: Step 7 | D17: Test keyboard access, screen-reader labels, color contrast, mobile layouts, page speed, links, and error states. | E17: Ongoing | F17: 0.2 | G17: Added reduced-motion support and updated concept journey copy. Full keyboard, screen-reader, contrast, mobile, speed, and error-state testing remains. | H17: 0.8
A18: P6-S08 | B18: Phase 6: Update and test the website | C18: Step 8 | D18: Keep search indexing disabled while the site is a concept; review metadata and enable indexing when the public offer is ready. | E18: Ongoing | F18: 0.5 | G18: Indexing remains disabled while the site is a concept; final metadata review and launch-time indexing decision remain. | H18: 0.5

Sheet Pending
A1: Pending Tasks
A2: Live view from Task Register; changes recalculate automatically.
A3: Task count | B3: =IFERROR(ROWS(_xlfn.ANCHORARRAY(A5)),0) -> 30 | D3: Average remaining | E3: =IFERROR(AVERAGE(_xlfn.ANCHORARRAY(H5)),0) -> 1
A4: Task ID | B4: Phase | C4: Plan Step | D4: Task | E4: Status | F4: Progress | G4: Notes | H4: Remaining
A5: {=_xlfn._xlws.FILTER('Task Register'!A2:G1001,'Task Register'!E2:E1001="Pending","")} -> P2-S05 | B5: Phase 2: Define the minimum useful toolkit | C5: Step 5 | D5: Choose the file formats based on how customers already work. | E5: Pending | F5: 0 | G5: Not yet confirmed as complete. Update this task in the Task Register as work progresses. | H5: {=_xlfn._xlws.FILTER('Task Register'!H2:H1001,'Task Register'!E2:E1001="Pending","")} -> 1
A6: P3-S01 | B6: Phase 3: Build and test a prototype | C6: Step 1 | D6: Create a rough but complete prototype of the minimum useful toolkit. | E6: Pending | F6: 0 | G6: Not yet confirmed as complete. Update this task in the Task Register as work progresses. | H6: 1
A7: P3-S02 | B7: Phase 3: Build and test a prototype | C7: Step 2 | D7: Use fictional or sanitized examples; do not include customer confidential information. | E7: Pending | F7: 0 | G7: Not yet confirmed as complete. Update this task in the Task Register as work progresses. | H7: 1
A8: P3-S03 | B8: Phase 3: Build and test a prototype | C8: Step 3 | D8: Ask 3â€“5 target users to complete a realistic task with the prototype. | E8: Pending | F8: 0 | G8: Not yet confirmed as complete. Update this task in the Task Register as work progresses. | H8: 1
A9: P3-S04 | B9: Phase 3: Build and test a prototype | C9: Step 4 | D9: Observe where they hesitate, misunderstand instructions, or need information that is missing. | E9: Pending | F9: 0 | G9: Not yet confirmed as complete. Update this task in the Task Register as work progresses. | H9: 1
A10: P3-S05 | B10: Phase 3: Build and test a prototype | C10: Step 5 | D10: Ask what they would change, what they would not use, and what they expected to be included. | E10: Pending | F10: 0 | G10: Not yet confirmed as complete. Update this task in the Task Register as work progresses. | H10: 1
A11: P3-S06 | B11: Phase 3: Build and test a prototype | C11: Step 6 | D11: Revise the toolkit and repeat the test for any major workflow changes. | E11: Pending | F11: 0 | G11: Not yet confirmed as complete. Update this task in the Task Register as work progresses. | H11: 1
A12: P3-S07 | B12: Phase 3: Build and test a prototype | C12: Step 7 | D12: Check that examples are clearly labeled and do not imply guaranteed security, compliance, or business results. | E12: Pending | F12: 0 | G12: Not yet confirmed as complete. Update this task in the Task Register as work progresses. | H12: 1
A13: P4-S01 | B13: Phase 4: Confirm the offer and price | C13: Step 1 | D13: Finalize the deliverables, formats, version, setup requirements, and compatibility notes. | E13: Pending | F13: 0 | G13: Not yet confirmed as complete. Update this task in the Task Register as work progresses. | H13: 1
A14: P4-S02 | B14: Phase 4: Confirm the offer and price | C14: Step 2 | D14: Estimate creation, maintenance, support, and delivery costs. | E14: Pending | F14: 0 | G14: Not yet confirmed as complete. Update this task in the Task Register as work progresses. | H14: 1
A15: P4-S03 | B15: Phase 4: Confirm the offer and price | C15: Step 3 | D15: Ask target users about the value and price expectations; compare these with costs and alternatives. | E15: Pending | F15: 0 | G15: Not yet confirmed as complete. Update this task in the Task Register as work progresses. | H15: 1
A16: P4-S04 | B16: Phase 4: Confirm the offer and price | C16: Step 4 | D16: Set an initial price only after confirming the product and delivery method. | E16: Pending | F16: 0 | G16: Not yet confirmed as complete. Update this task in the Task Register as work progresses. | H16: 1
A17: P4-S05 | B17: Phase 4: Confirm the offer and price | C17: Step 5 | D17: Define what customers receive, how updates work, what support is included, and any usage limits. | E17: Pending | F17: 0 | G17: Not yet confirmed as complete. Update this task in the Task Register as work progresses. | H17: 1
... A34: P7-S07 | B34: Phase 7: Launch and learn | C34: Step 7 | D34: Decide whether to improve the first toolkit, build the next individual toolkit, or create a bundle. | E34: Pending | F34: 0 | G34: Not yet confirmed as complete. Update this task in the Task Register as work progresses. | H34: 1

Sheet Completed
A1: Completed Tasks
A2: Live view from Task Register; changes recalculate automatically.
A3: Task count | B3: =IFERROR(ROWS(_xlfn.ANCHORARRAY(A5)),0) -> 3 | D3: Average remaining | E3: =IFERROR(AVERAGE(_xlfn.ANCHORARRAY(H5)),0) -> 0
A4: Task ID | B4: Phase | C4: Plan Step | D4: Task | E4: Status | F4: Progress | G4: Notes | H4: Remaining
A5: {=_xlfn._xlws.FILTER('Task Register'!A2:G1001,'Task Register'!E2:E1001="Completed","")} -> SETUP-01 | B5: Project setup | C5: Completed deliverable | D5: Create the detailed seven-phase project plan and Microsoft Project-compatible schedule. | E5: Completed | F5: 1 | G5: The plan and schedule have been created; this workbook provides the step-by-step status tracker. | H5: {=_xlfn._xlws.FILTER('Task Register'!H2:H1001,'Task Register'!E2:E1001="Completed","")} -> 0
A6: P1-S01 | B6: Phase 1: Choose and validate the customer problem | C6: Step 1 | D6: List the likely customer roles for the Application Review Kit, such as application security engineers and software teams. | E6: Completed | F6: 1 | G6: Role list created. Primary audience selected: AppSec engineer/reviewer at a small software team. Other likely roles: software engineering lead/tech lead doing self-reviews; independent application-security consultant; AppSec/product-security lead at a larger company. Treat all as hypotheses pending customer conversations. | H6: 0
A7: P6-S03 | B7: Phase 6: Update and test the website | C7: Step 3 | D7: Make product previews clearly distinguish illustrative examples from actual downloadable deliverables. | E7: Completed | F7: 1 | G7: Previews are labeled as illustrative concepts, not downloadable products. | H7: 0

Sheet Pivot Tables
A1: PivotTable Summaries
A2: Refresh All after changing statuses in the Task Register.
A4: Task Count | B4: Status | J4: Status | K4: Task Count
A5: Phase | B5: Completed | C5: Ongoing | D5: Pending | E5: Grand Total | J5: Completed | K5: 3
A6: Phase 1: Choose and validate the customer problem | B6: 1 | C6: 5 | E6: 6 | J6: Ongoing | K6: 14
A7: Phase 2: Define the minimum useful toolkit | C7: 5 | D7: 1 | E7: 6 | J7: Pending | K7: 30
A8: Phase 3: Build and test a prototype | D8: 7 | E8: 7 | J8: Grand Total | K8: 47
A9: Phase 4: Confirm the offer and price | D9: 6 | E9: 6
A10: Phase 5: Prepare business and customer operations | D10: 6 | E10: 6
A11: Phase 6: Update and test the website | B11: 1 | C11: 4 | D11: 3 | E11: 8
A12: Phase 7: Launch and learn | D12: 7 | E12: 7
A13: Project setup | B13: 1 | E13: 1
A14: Grand Total | B14: 3 | C14: 14 | D14: 30 | E14: 47
A18: Live Phase Summary (updates immediately)
A19: Phase | B19: Completed | C19: Ongoing | D19: Pending | E19: Total tasks | F19: Average remaining
A20: Project setup | B20: =COUNTIFS('Task Register'!B2:B1001,A20,'Task Register'!E2:E1001,B$19) -> 1 | C20: =COUNTIFS('Task Register'!B2:B1001,A20,'Task Register'!E2:E1001,C$19) -> 0 | D20: =COUNTIFS('Task Register'!B2:B1001,A20,'Task Register'!E2:E1001,D$19) -> 0 | E20: =SUM(B20) -> 1 | F20: =IFERROR(AVERAGEIFS('Task Register'!H2:H1001,'Task Register'!B2:B1001,A20),0) -> 0
A21: Phase 1: Choose and validate the customer problem | B21: =COUNTIFS('Task Register'!B2:B1001,A21,'Task Register'!E2:E1001,B$19) -> 1 | C21: =COUNTIFS('Task Register'!B2:B1001,A21,'Task Register'!E2:E1001,C$19) -> 5 | D21: =COUNTIFS('Task Register'!B2:B1001,A21,'Task Register'!E2:E1001,D$19) -> 0 | E21: =SUM(B21) -> 1 | F21: =IFERROR(AVERAGEIFS('Task Register'!H2:H1001,'Task Register'!B2:B1001,A21),0) -> 0.68333333
A22: Phase 2: Define the minimum useful toolkit | B22: =COUNTIFS('Task Register'!B2:B1001,A22,'Task Register'!E2:E1001,B$19) -> 0 | C22: =COUNTIFS('Task Register'!B2:B1001,A22,'Task Register'!E2:E1001,C$19) -> 5 | D22: =COUNTIFS('Task Register'!B2:B1001,A22,'Task Register'!E2:E1001,D$19) -> 1 | E22: =SUM(B22) -> 0 | F22: =IFERROR(AVERAGEIFS('Task Register'!H2:H1001,'Task Register'!B2:B1001,A22),0) -> 0.79166667
A23: Phase 3: Build and test a prototype | B23: =COUNTIFS('Task Register'!B2:B1001,A23,'Task Register'!E2:E1001,B$19) -> 0 | C23: =COUNTIFS('Task Register'!B2:B1001,A23,'Task Register'!E2:E1001,C$19) -> 0 | D23: =COUNTIFS('Task Register'!B2:B1001,A23,'Task Register'!E2:E1001,D$19) -> 7 | E23: =SUM(B23) -> 0 | F23: =IFERROR(AVERAGEIFS('Task Register'!H2:H1001,'Task Register'!B2:B1001,A23),0) -> 1
A24: Phase 4: Confirm the offer and price | B24: =COUNTIFS('Task Register'!B2:B1001,A24,'Task Register'!E2:E1001,B$19) -> 0 | C24: =COUNTIFS('Task Register'!B2:B1001,A24,'Task Register'!E2:E1001,C$19) -> 0 | D24: =COUNTIFS('Task Register'!B2:B1001,A24,'Task Register'!E2:E1001,D$19) -> 6 | E24: =SUM(B24) -> 0 | F24: =IFERROR(AVERAGEIFS('Task Register'!H2:H1001,'Task Register'!B2:B1001,A24),0) -> 1
A25: Phase 5: Prepare business and customer operations | B25: =COUNTIFS('Task Register'!B2:B1001,A25,'Task Register'!E2:E1001,B$19) -> 0 | C25: =COUNTIFS('Task Register'!B2:B1001,A25,'Task Register'!E2:E1001,C$19) -> 0 | D25: =COUNTIFS('Task Register'!B2:B1001,A25,'Task Register'!E2:E1001,D$19) -> 6 | E25: =SUM(B25) -> 0 | F25: =IFERROR(AVERAGEIFS('Task Register'!H2:H1001,'Task Register'!B2:B1001,A25),0) -> 1
A26: Phase 6: Update and test the website | B26: =COUNTIFS('Task Register'!B2:B1001,A26,'Task Register'!E2:E1001,B$19) -> 1 | C26: =COUNTIFS('Task Register'!B2:B1001,A26,'Task Register'!E2:E1001,C$19) -> 4 | D26: =COUNTIFS('Task Register'!B2:B1001,A26,'Task Register'!E2:E1001,D$19) -> 3 | E26: =SUM(B26) -> 1 | F26: =IFERROR(AVERAGEIFS('Task Register'!H2:H1001,'Task Register'!B2:B1001,A26),0) -> 0.6625
A27: Phase 7: Launch and learn | B27: =COUNTIFS('Task Register'!B2:B1001,A27,'Task Register'!E2:E1001,B$19) -> 0 | C27: =COUNTIFS('Task Register'!B2:B1001,A27,'Task Register'!E2:E1001,C$19) -> 0 | D27: =COUNTIFS('Task Register'!B2:B1001,A27,'Task Register'!E2:E1001,D$19) -> 7 | E27: =SUM(B27) -> 0 | F27: =IFERROR(AVERAGEIFS('Task Register'!H2:H1001,'Task Register'!B2:B1001,A27),0) -> 1
A28: TOTAL | B28: =SUM(B20:B27) -> 3 | C28: =SUM(C20:C27) -> 14 | D28: =SUM(D20:D27) -> 30 | E28: =SUM(E20:E27) -> 3 | F28: =IFERROR(AVERAGE('Task Register'!H2:H1001),0) -> 0.85425532
A30: Formula-driven counts and remaining percentages recalculate immediately. PivotTables above refresh when the workbook opens or with Data > Refresh All.

Sheet Task Register
A1: Task ID | B1: Phase | C1: Plan Step | D1: Task | E1: Status | F1: Progress | G1: Notes | H1: Remaining
A2: SETUP-01 | B2: Project setup | C2: Completed deliverable | D2: Create the detailed seven-phase project plan and Microsoft Project-compatible schedule. | E2: Completed | F2: 1 | G2: The plan and schedule have been created; this workbook provides the step-by-step status tracker. | H2: =1-ProjectTaskRegister[[#This Row],[Progress]] -> 0
A3: P1-S01 | B3: Phase 1: Choose and validate the customer problem | C3: Step 1 | D3: List the likely customer roles for the Application Review Kit, such as application security engineers and software teams. | E3: Completed | F3: 1 | G3: Role list created. Primary audience selected: AppSec engineer/reviewer at a small software team. Other likely roles: software engineering lead/tech lead doing self-reviews; independent application-security consultant; AppSec/product-security lead at a larger company. Treat all as hypotheses pending customer conversations. | H3: =1-ProjectTaskRegister[[#This Row],[Progress]] -> 0
A4: P1-S02 | B4: Phase 1: Choose and validate the customer problem | C4: Step 2 | D4: Choose one primary audience and describe its review workflow, current tools, and pain points. | E4: Ongoing | F4: 0.5 | G4: Drafted P1-S02-Audience-Workflow-Hypothesis.md: selected AppSec reviewer at a small software team; documented a likely review workflow, tool categories, and pain-point hypotheses. These are not verified customer facts. Update after interviews with 5-8 target users. | H4: =1-ProjectTaskRegister[[#This Row],[Progress]] -> 0.5
A5: P1-S03 | B5: Phase 1: Choose and validate the customer problem | C5: Step 3 | D5: Speak with 5â€“8 people who match that audience. Ask about their current process, where work slows down, what they already use, and what would make a toolkit useful. | E5: Ongoing | F5: 0.1 | G5: Prepared P1-S03-Customer-Interview-Guide.md, neutral 25-30 minute interview script, invitation template, privacy guidance, synthesis criteria, and an eight-person Interview Log tab. No interviews have been conducted yet; this is preparation only. | H5: =1-ProjectTaskRegister[[#This Row],[Progress]] -> 0.9
A6: P1-S04 | B6: Phase 1: Choose and validate the customer problem | C6: Step 4 | D6: Avoid pitching the proposed product during the first part of each conversation; learn how customers work today. | E6: Ongoing | F6: 0.1 | G6: Added a P1-S04 current-process-first protocol to the interview guide: keep the product out of the opening/workflow questions, defer the optional concept probe until the last 2-3 minutes, and log deviations. No interviews have been conducted; preparation only. | H6: =1-ProjectTaskRegister[[#This Row],[Progress]] -> 0.9
A7: P1-S05 | B7: Phase 1: Choose and validate the customer problem | C7: Step 5 | D7: Summarize repeated needs, objections, existing alternatives, and language customers use. | E7: Ongoing | F7: 0.1 | G7: User-supplied fictional interview scenarios are in separate Practice tabs for rehearsal. They are not actual interviews or evidence; Interview Log remains at zero. P1-S05 remains ongoing pending real interview findings. | H7: =1-ProjectTaskRegister[[#This Row],[Progress]] -> 0.9
A8: P1-S06 | B8: Phase 1: Choose and validate the customer problem | C8: Step 6 | D8: Decide whether to proceed, revise the audience/problem, or test another toolkit idea. | E8: Ongoing | F8: 0.1 | G8: Prepared P1-S06-Customer-Problem-Decision-Framework.md with proceed, revise, retarget, and pause criteria. The actual decision remains blocked until at least five qualified customer interviews and synthesis are complete. | H8: =1-ProjectTaskRegister[[#This Row],[Progress]] -> 0.9
A9: P2-S01 | B9: Phase 2: Define the minimum useful toolkit | C9: Step 1 | D9: Write a one-sentence product promise focused on a practical task, not a guaranteed security outcome. | E9: Ongoing | F9: 0.25 | G9: Drafted a one-sentence workflow-support promise in P2-Application-Review-Kit-Product-Brief.md. Validate wording and problem importance with target users before finalizing. | H9: =1-ProjectTaskRegister[[#This Row],[Progress]] -> 0.75
A10: P2-S02 | B10: Phase 2: Define the minimum useful toolkit | C10: Step 2 | D10: Define the intended user, prerequisites, and situations where the toolkit is not suitable. | E10: Ongoing | F10: 0.25 | G10: Provisional intended user, prerequisites, and exclusions drafted in P2-Application-Review-Kit-Product-Brief.md. Audience and workflow remain unvalidated hypotheses. | H10: =1-ProjectTaskRegister[[#This Row],[Progress]] -> 0.75
A11: P2-S03 | B11: Phase 2: Define the minimum useful toolkit | C11: Step 3 | D11: Select only the worksheets, checklists, and templates necessary to complete the task. | E11: Ongoing | F11: 0.25 | G11: Six candidate resources in the existing catalog were organized as a provisional minimum set in P2-Application-Review-Kit-Product-Brief.md. Include/remove decisions await interviews and prototype feedback. | H11: =1-ProjectTaskRegister[[#This Row],[Progress]] -> 0.75
A12: P2-S04 | B12: Phase 2: Define the minimum useful toolkit | C12: Step 4 | D12: Describe the expected workflow: what the user provides, what they do with each resource, and what they finish with. | E12: Ongoing | F12: 0.3 | G12: Drafted a five-step intake-to-remediation workflow and expected outputs in P2-Application-Review-Kit-Product-Brief.md. Confirm with real users before treating as final. | H12: =1-ProjectTaskRegister[[#This Row],[Progress]] -> 0.7
A13: P2-S05 | B13: Phase 2: Define the minimum useful toolkit | C13: Step 5 | D13: Choose the file formats based on how customers already work. | E13: Pending | F13: 0 | G13: Not yet confirmed as complete. Update this task in the Task Register as work progresses. | H13: =1-ProjectTaskRegister[[#This Row],[Progress]] -> 1
... A48: P7-S07 | B48: Phase 7: Launch and learn | C48: Step 7 | D48: Decide whether to improve the first toolkit, build the next individual toolkit, or create a bundle. | E48: Pending | F48: 0 | G48: Not yet confirmed as complete. Update this task in the Task Register as work progresses. | H48: =1-ProjectTaskRegister[[#This Row],[Progress]] -> 1

Sheet Update Guide
A1: How to keep this project tracker live
A3: Single source of truth | B3: Update task status, progress, and evidence in Task Register. Completed, Ongoing, and Pending views and Phase Tracker formulas recalculate from it.
A4: Task status | B4: Use the dropdown: Pending, Ongoing, or Completed. Set Completed only when the step is actually done and supported in Notes.
A5: Task progress | B5: Enter 0%–100% in Progress. Remaining is calculated automatically. A Completed status alone does not satisfy the phase completion gate if Progress is below 100%.
A6: Phase completion | B6: Phase Tracker calculates counts and percentages. Select Yes in Exit check verified? only when the listed exit criterion is supported by evidence. Phase status becomes Complete only when every phase task is Completed, every task is 100%, and the exit check is Yes.
A7: Real customer research | B7: Enter only real conversations in Interview Log using anonymous IDs. Simulated material lives on Practice tabs and must never be counted as interview evidence.
A8: Interview synthesis | B8: Use Interview Synthesis for evidence-backed themes, distinct participant counts, unprompted counts, alternatives, objections, and interpretation. Keep unsupported fields blank.
A9: PivotTables | B9: Formula-driven phase and status views recalculate immediately. Native PivotTables refresh when the workbook opens; use Data > Refresh All for a manual refresh.
A10: Assistant updates | B10: When a task or exit criterion is complete, tell the assistant the task ID, what was done, and which evidence/deliverable supports it. The assistant will update this same workbook and its dependent tabs. This workbook is a local file, not a cloud collaboration service.
A12: Current constraint | B12: Interview Log currently has zero real completed interviews. Simulated scenarios do not complete Phase 1 or customer-evidence tasks.

Sheet Phase Tracker
A1: CAB Synergy | Live Phase Tracker
A2: Task Register is the source of truth. Task counts and percentages update automatically. A phase becomes Complete only when all its tasks are Completed at 100% and the exit check is explicitly verified.
A4: Phase | B4: Tasks | C4: Completed | D4: Ongoing | E4: Pending | F4: Average progress | G4: Average remaining | H4: All tasks at 100% | I4: Exit check verified? | J4: Phase status | K4: Exit check / completion evidence
A5: Phase 1: Choose and validate the customer problem | B5: =COUNTIF('Task Register'!$B$2:$B$1001,A5) -> 6 | C5: =COUNTIFS('Task Register'!$B$2:$B$1001,A5,'Task Register'!$E$2:$E$1001,"Completed") -> 1 | D5: =COUNTIFS('Task Register'!$B$2:$B$1001,A5,'Task Register'!$E$2:$E$1001,"Ongoing") -> 5 | E5: =COUNTIFS('Task Register'!$B$2:$B$1001,A5,'Task Register'!$E$2:$E$1001,"Pending") -> 0 | F5: =IFERROR(AVERAGEIF('Task Register'!$B$2:$B$1001,A5,'Task Register'!$F$2:$F$1001),0) -> 0.31666667 | G5: =1-F5 -> 0.68333333 | H5: =COUNTIFS('Task Register'!$B$2:$B$1001,A5,'Task Register'!$F$2:$F$1001,">=1") -> 1 | I5: No | J5: =IF(B5=0,"No tasks",IF(AND(C5=B5,H5=B5,I5="Yes"),"Complete",IF(AND(C5=B5,H5=B5),"Ready for exit review",IF(SUMIF('Task Register'!$B$2:$B$1001,A5,'Task Register'!$F$2:$F$1001)=0,"Not started","In progress")))) -> In progress | K5: Multiple target users independently describe the problem and the proposed toolkit addresses a clear gap.
A6: Phase 2: Define the minimum useful toolkit | B6: =COUNTIF('Task Register'!$B$2:$B$1001,A6) -> 6 | C6: =COUNTIFS('Task Register'!$B$2:$B$1001,A6,'Task Register'!$E$2:$E$1001,"Completed") -> 0 | D6: =COUNTIFS('Task Register'!$B$2:$B$1001,A6,'Task Register'!$E$2:$E$1001,"Ongoing") -> 5 | E6: =COUNTIFS('Task Register'!$B$2:$B$1001,A6,'Task Register'!$E$2:$E$1001,"Pending") -> 1 | F6: =IFERROR(AVERAGEIF('Task Register'!$B$2:$B$1001,A6,'Task Register'!$F$2:$F$1001),0) -> 0.20833333 | G6: =1-F6 -> 0.79166667 | H6: =COUNTIFS('Task Register'!$B$2:$B$1001,A6,'Task Register'!$F$2:$F$1001,">=1") -> 0 | I6: No | J6: =IF(B6=0,"No tasks",IF(AND(C6=B6,H6=B6,I6="Yes"),"Complete",IF(AND(C6=B6,H6=B6),"Ready for exit review",IF(SUMIF('Task Register'!$B$2:$B$1001,A6,'Task Register'!$F$2:$F$1001)=0,"Not started","In progress")))) -> In progress | K6: A target user can explain what the toolkit does, who it is for, and what it does not promise.
A7: Phase 3: Build and test a prototype | B7: =COUNTIF('Task Register'!$B$2:$B$1001,A7) -> 7 | C7: =COUNTIFS('Task Register'!$B$2:$B$1001,A7,'Task Register'!$E$2:$E$1001,"Completed") -> 0 | D7: =COUNTIFS('Task Register'!$B$2:$B$1001,A7,'Task Register'!$E$2:$E$1001,"Ongoing") -> 0 | E7: =COUNTIFS('Task Register'!$B$2:$B$1001,A7,'Task Register'!$E$2:$E$1001,"Pending") -> 7 | F7: =IFERROR(AVERAGEIF('Task Register'!$B$2:$B$1001,A7,'Task Register'!$F$2:$F$1001),0) -> 0 | G7: =1-F7 -> 1 | H7: =COUNTIFS('Task Register'!$B$2:$B$1001,A7,'Task Register'!$F$2:$F$1001,">=1") -> 0 | I7: No | J7: =IF(B7=0,"No tasks",IF(AND(C7=B7,H7=B7,I7="Yes"),"Complete",IF(AND(C7=B7,H7=B7),"Ready for exit review",IF(SUMIF('Task Register'!$B$2:$B$1001,A7,'Task Register'!$F$2:$F$1001)=0,"Not started","In progress")))) -> Not started | K7: Test users can complete the intended task without step-by-step help; important gaps are resolved or documented.
A8: Phase 4: Confirm the offer and price | B8: =COUNTIF('Task Register'!$B$2:$B$1001,A8) -> 6 | C8: =COUNTIFS('Task Register'!$B$2:$B$1001,A8,'Task Register'!$E$2:$E$1001,"Completed") -> 0 | D8: =COUNTIFS('Task Register'!$B$2:$B$1001,A8,'Task Register'!$E$2:$E$1001,"Ongoing") -> 0 | E8: =COUNTIFS('Task Register'!$B$2:$B$1001,A8,'Task Register'!$E$2:$E$1001,"Pending") -> 6 | F8: =IFERROR(AVERAGEIF('Task Register'!$B$2:$B$1001,A8,'Task Register'!$F$2:$F$1001),0) -> 0 | G8: =1-F8 -> 1 | H8: =COUNTIFS('Task Register'!$B$2:$B$1001,A8,'Task Register'!$F$2:$F$1001,">=1") -> 0 | I8: No | J8: =IF(B8=0,"No tasks",IF(AND(C8=B8,H8=B8,I8="Yes"),"Complete",IF(AND(C8=B8,H8=B8),"Ready for exit review",IF(SUMIF('Task Register'!$B$2:$B$1001,A8,'Task Register'!$F$2:$F$1001)=0,"Not started","In progress")))) -> Not started | K8: CAB Synergy can reliably deliver exactly what the offer describes and support the stated terms.
A9: Phase 5: Prepare business and customer operations | B9: =COUNTIF('Task Register'!$B$2:$B$1001,A9) -> 6 | C9: =COUNTIFS('Task Register'!$B$2:$B$1001,A9,'Task Register'!$E$2:$E$1001,"Completed") -> 0 | D9: =COUNTIFS('Task Register'!$B$2:$B$1001,A9,'Task Register'!$E$2:$E$1001,"Ongoing") -> 0 | E9: =COUNTIFS('Task Register'!$B$2:$B$1001,A9,'Task Register'!$E$2:$E$1001,"Pending") -> 6 | F9: =IFERROR(AVERAGEIF('Task Register'!$B$2:$B$1001,A9,'Task Register'!$F$2:$F$1001),0) -> 0 | G9: =1-F9 -> 1 | H9: =COUNTIFS('Task Register'!$B$2:$B$1001,A9,'Task Register'!$F$2:$F$1001,">=1") -> 0 | I9: No | J9: =IF(B9=0,"No tasks",IF(AND(C9=B9,H9=B9,I9="Yes"),"Complete",IF(AND(C9=B9,H9=B9),"Ready for exit review",IF(SUMIF('Task Register'!$B$2:$B$1001,A9,'Task Register'!$F$2:$F$1001)=0,"Not started","In progress")))) -> Not started | K9: Signup and checkout remain disabled until data handling, policies, and fulfillment workflows are ready.
A10: Phase 6: Update and test the website | B10: =COUNTIF('Task Register'!$B$2:$B$1001,A10) -> 8 | C10: =COUNTIFS('Task Register'!$B$2:$B$1001,A10,'Task Register'!$E$2:$E$1001,"Completed") -> 1 | D10: =COUNTIFS('Task Register'!$B$2:$B$1001,A10,'Task Register'!$E$2:$E$1001,"Ongoing") -> 4 | E10: =COUNTIFS('Task Register'!$B$2:$B$1001,A10,'Task Register'!$E$2:$E$1001,"Pending") -> 3 | F10: =IFERROR(AVERAGEIF('Task Register'!$B$2:$B$1001,A10,'Task Register'!$F$2:$F$1001),0) -> 0.3375 | G10: =1-F10 -> 0.6625 | H10: =COUNTIFS('Task Register'!$B$2:$B$1001,A10,'Task Register'!$F$2:$F$1001,">=1") -> 1 | I10: No | J10: =IF(B10=0,"No tasks",IF(AND(C10=B10,H10=B10,I10="Yes"),"Complete",IF(AND(C10=B10,H10=B10),"Ready for exit review",IF(SUMIF('Task Register'!$B$2:$B$1001,A10,'Task Register'!$F$2:$F$1001)=0,"Not started","In progress")))) -> In progress | K10: A first-time visitor can explain who the toolkit is for, what it includes, its availability, and what action they can take.
A11: Phase 7: Launch and learn | B11: =COUNTIF('Task Register'!$B$2:$B$1001,A11) -> 7 | C11: =COUNTIFS('Task Register'!$B$2:$B$1001,A11,'Task Register'!$E$2:$E$1001,"Completed") -> 0 | D11: =COUNTIFS('Task Register'!$B$2:$B$1001,A11,'Task Register'!$E$2:$E$1001,"Ongoing") -> 0 | E11: =COUNTIFS('Task Register'!$B$2:$B$1001,A11,'Task Register'!$E$2:$E$1001,"Pending") -> 7 | F11: =IFERROR(AVERAGEIF('Task Register'!$B$2:$B$1001,A11,'Task Register'!$F$2:$F$1001),0) -> 0 | G11: =1-F11 -> 1 | H11: =COUNTIFS('Task Register'!$B$2:$B$1001,A11,'Task Register'!$F$2:$F$1001,">=1") -> 0 | I11: No | J11: =IF(B11=0,"No tasks",IF(AND(C11=B11,H11=B11,I11="Yes"),"Complete",IF(AND(C11=B11,H11=B11),"Ready for exit review",IF(SUMIF('Task Register'!$B$2:$B$1001,A11,'Task Register'!$F$2:$F$1001)=0,"Not started","In progress")))) -> Not started | K11: Fulfillment is reliable and customer feedback supports the next investment.
A13: Checking Yes is an explicit confirmation that the exit criterion was reviewed and met. Simulated scenarios are not customer evidence. Keep signup and checkout disabled until Phase 5 readiness is verified.

Sheet Overview
A1: CAB Synergy | Project Plan Progress Tracker
A2: Status baseline: October 2, 2026 | 47 task rows across the plan and setup
A4: Status | B4: Task count | D4: Progress indicator | E4: Value
A5: Completed | B5: =COUNTIF('Task Register'!E:E,A5) -> 3 | D5: Average task progress | E5: =IFERROR(AVERAGE('Task Register'!F2:F1001),0) -> 0.14574468
A6: Ongoing | B6: =COUNTIF('Task Register'!E:E,A6) -> 14 | D6: Total tracked tasks | E6: =COUNTA('Task Register'!A2:A1001) -> 47
A7: Pending | B7: =COUNTIF('Task Register'!E:E,A7) -> 30 | D7: Average remaining | E7: =1-E5 -> 0.85425532
A10: How to use this workbook
A11: Task Register is the source of truth. Change Status or Progress there; the Completed, Pending, and Ongoing tabs and percentages recalculate automatically. PivotTables refresh when the workbook opens; use Data > Refresh All to refresh them manually.
A13: Status definitions
A14: Completed = evidence in the project history supports completion. Ongoing = work has started but the full plan step still has follow-up. Pending = no completion evidence yet; pending does not necessarily mean the work is scheduled.
A16: Signup remains pending by choice until a service/link is available. The October 5–December 15, 2026 schedule window is an editable estimate, not a confirmed commitment.
A18: Phase completion is gated
A19: Open the Phase Tracker. Progress and task counts are live; a phase is Complete only when all its tasks are 100% and its exit check is verified.
